layered_config/__init__.py
layered_config-2.0.3.dist-info/WHEEL
layered_config-2.0.3.dist-info/METADATA
layered_config-2.0.3.dist-info/RECORD
